asyncio/base_events.py
asyncio/base_subprocess.py
asyncio/constants.py
asyncio/coroutines.py
asyncio/events.py
asyncio/futures.py
asyncio/locks.py
asyncio/log.py
asyncio/proactor_events.py
asyncio/protocols.py
asyncio/queues.py
asyncio/selectors.py
asyncio/selector_events.py
asyncio/streams.py
asyncio/subprocess.py
asyncio/tasks.py
asyncio/test_utils.py
asyncio/transports.py
asyncio/unix_events.py
asyncio/windows_events.py
asyncio/windows_utils.py
asyncio/_overlapped.pyd
asyncio/__init__.py
asyncio-3.4.2.dist-info/DESCRIPTION.rst
asyncio-3.4.2.dist-info/METADATA
asyncio-3.4.2.dist-info/metadata.json
asyncio-3.4.2.dist-info/RECORD
asyncio-3.4.2.dist-info/top_level.txt
asyncio-3.4.2.dist-info/WHEEL
