Metadata-Version: 2.0
Name: asyncio
Version: 3.4.2
Summary: reference implementation of PEP 3156
Home-page: http://www.python.org/dev/peps/pep-3156/
Author: UNKNOWN
Author-email: UNKNOWN
License: UNKNOWN
Platform: UNKNOWN
Classifier: Programming Language :: Python
Classifier: Programming Language :: Python :: 3
Classifier: Programming Language :: Python :: 3.3
